automlplforidps/__init__.py
automlplforidps/pipeline.py
automlplforidps-1.1.1.dist-info/WHEEL
automlplforidps-1.1.1.dist-info/entry_points.txt
automlplforidps-1.1.1.dist-info/METADATA
automlplforidps-1.1.1.dist-info/RECORD
