Metadata-Version: 2.3
Name: automlplforidps
Version: 1.1.1
Summary: A robust, automated pipeline for multiclass classification tasks.
Author: RAGHAVVRAM JOHNSON
Author-email: RAGHAVVRAM JOHNSON <raghavvram.johnson@gmail.com>
License: MIT License
Classifier: Programming Language :: Python :: 3
Classifier: License :: OSI Approved :: MIT License
Classifier: Operating System :: OS Independent
Classifier: Topic :: Scientific/Engineering :: Artificial Intelligence
Requires-Dist: pandas
Requires-Dist: scikit-learn
Requires-Dist: imbalanced-learn
Requires-Dist: xgboost
Requires-Dist: catboost
Requires-Dist: zoofs
Requires-Dist: scikit-optimize
Requires-Dist: numpy
Requires-Dist: lightgbm
Requires-Python: >=3.12
